pheidi/.DS_Store
pheidi/__init__.py
pheidi/pheidi.py
pheidi-0.0.15.dist-info/WHEEL
pheidi-0.0.15.dist-info/METADATA
pheidi-0.0.15.dist-info/RECORD
