Metadata-Version: 2.1
Name: pheidi
Version: 0.0.15
Summary: Fast In Ram Memory
License: MIT
Author: Austin
Requires-Python: >=3.8,<4.0
Classifier: License :: OSI Approved :: MIT License
Classifier: Programming Language :: Python :: 3
Classifier: Programming Language :: Python :: 3.8
Classifier: Programming Language :: Python :: 3.9
Requires-Dist: msgpack (>=1.0.2,<2.0.0)
Requires-Dist: msgpack-numpy (>=0.4.7,<0.5.0)
